setup.py
aspace/__init__.py
aspace/aspace.py
aspace.egg-info/PKG-INFO
aspace.egg-info/SOURCES.txt
aspace.egg-info/dependency_links.txt
aspace.egg-info/not-zip-safe
aspace.egg-info/requires.txt
aspace.egg-info/top_level.txt