Metadata-Version: 1.2
Name: aspace
Version: 1.6
Summary: Client for working with REST API for ArchivesSpace
Home-page: https://github.com/polkmetadatalib/aspace
Author: Patrick Harrington
Author-email: harringp@uwosh.edu
License: MIT
Platform: UNKNOWN
Requires-Python: >=3
